stockclock/MarketView.py
stockclock/Sentiment.py
stockclock/_DevUtils.py
stockclock/__init__.py
stockclock/Sample/__init__.py
stockclock/Sample/technicalSample.parquet
stockclock/Technical/Trend.py
stockclock/Technical/__init__.py
stock_clock-0.0.15.dist-info/LICENSE
stock_clock-0.0.15.dist-info/METADATA
stock_clock-0.0.15.dist-info/WHEEL
stock_clock-0.0.15.dist-info/top_level.txt
stock_clock-0.0.15.dist-info/RECORD
